{"nodes": [{"id": "f_dev_clover_apps_backend_src_memory_memory_service_ts", "label": "memory.service.ts", "file_type": "code", "source_file": "F:\\Dev\\Clover\\apps\\backend\\src\\memory\\memory.service.ts", "source_location": "L1"}, {"id": "memory_memory_service_search", "label": "search()", "file_type": "code", "source_file": "F:\\Dev\\Clover\\apps\\backend\\src\\memory\\memory.service.ts", "source_location": "L14"}, {"id": "memory_memory_service_indextext", "label": "indexText()", "file_type": "code", "source_file": "F:\\Dev\\Clover\\apps\\backend\\src\\memory\\memory.service.ts", "source_location": "L28"}, {"id": "memory_memory_service_indexfile", "label": "indexFile()", "file_type": "code", "source_file": "F:\\Dev\\Clover\\apps\\backend\\src\\memory\\memory.service.ts", "source_location": "L43"}, {"id": "memory_memory_service_ingestdirectory", "label": "ingestDirectory()", "file_type": "code", "source_file": "F:\\Dev\\Clover\\apps\\backend\\src\\memory\\memory.service.ts", "source_location": "L56"}, {"id": "memory_memory_service_writenote", "label": "writeNote()", "file_type": "code", "source_file": "F:\\Dev\\Clover\\apps\\backend\\src\\memory\\memory.service.ts", "source_location": "L70"}, {"id": "memory_memory_service_tovectorchunks", "label": "toVectorChunks()", "file_type": "code", "source_file": "F:\\Dev\\Clover\\apps\\backend\\src\\memory\\memory.service.ts", "source_location": "L84"}], "edges": [{"source": "f_dev_clover_apps_backend_src_memory_memory_service_ts", "target": "promises", "relation": "imports_from", "context": "import", "confidence": "EXTRACTED", "source_file": "F:\\Dev\\Clover\\apps\\backend\\src\\memory\\memory.service.ts", "source_location": "L1", "weight": 1.0}, {"source": "f_dev_clover_apps_backend_src_memory_memory_service_ts", "target": "node_path", "relation": "imports_from", "context": "import", "confidence": "EXTRACTED", "source_file": "F:\\Dev\\Clover\\apps\\backend\\src\\memory\\memory.service.ts", "source_location": "L2", "weight": 1.0}, {"source": "f_dev_clover_apps_backend_src_memory_memory_service_ts", "target": "shared", "relation": "imports_from", "context": "import", "confidence": "EXTRACTED", "source_file": "F:\\Dev\\Clover\\apps\\backend\\src\\memory\\memory.service.ts", "source_location": "L3", "weight": 1.0}, {"source": "f_dev_clover_apps_backend_src_memory_memory_service_ts", "target": "f_dev_clover_apps_backend_src_config_config_ts", "relation": "imports_from", "context": "import", "confidence": "EXTRACTED", "source_file": "F:\\Dev\\Clover\\apps\\backend\\src\\memory\\memory.service.ts", "source_location": "L4", "weight": 1.0}, {"source": "f_dev_clover_apps_backend_src_memory_memory_service_ts", "target": "config_config_config", "relation": "imports", "context": "import", "confidence": "EXTRACTED", "source_file": "F:\\Dev\\Clover\\apps\\backend\\src\\memory\\memory.service.ts", "source_location": "L4", "weight": 1.0}, {"source": "f_dev_clover_apps_backend_src_memory_memory_service_ts", "target": "f_dev_clover_apps_backend_src_memory_chunker_ts", "relation": "imports_from", "context": "import", "confidence": "EXTRACTED", "source_file": "F:\\Dev\\Clover\\apps\\backend\\src\\memory\\memory.service.ts", "source_location": "L5", "weight": 1.0}, {"source": "f_dev_clover_apps_backend_src_memory_memory_service_ts", "target": "memory_chunker_split", "relation": "imports", "context": "import", "confidence": "EXTRACTED", "source_file": "F:\\Dev\\Clover\\apps\\backend\\src\\memory\\memory.service.ts", "source_location": "L5", "weight": 1.0}, {"source": "f_dev_clover_apps_backend_src_memory_memory_service_ts", "target": "f_dev_clover_apps_backend_src_memory_embedder_ts", "relation": "imports_from", "context": "import", "confidence": "EXTRACTED", "source_file": "F:\\Dev\\Clover\\apps\\backend\\src\\memory\\memory.service.ts", "source_location": "L6", "weight": 1.0}, {"source": "f_dev_clover_apps_backend_src_memory_memory_service_ts", "target": "memory_embedder_embed", "relation": "imports", "context": "import", "confidence": "EXTRACTED", "source_file": "F:\\Dev\\Clover\\apps\\backend\\src\\memory\\memory.service.ts", "source_location": "L6", "weight": 1.0}, {"source": "f_dev_clover_apps_backend_src_memory_memory_service_ts", "target": "f_dev_clover_apps_backend_src_memory_lancedb_adapter_ts", "relation": "imports_from", "context": "import", "confidence": "EXTRACTED", "source_file": "F:\\Dev\\Clover\\apps\\backend\\src\\memory\\memory.service.ts", "source_location": "L7", "weight": 1.0}, {"source": "f_dev_clover_apps_backend_src_memory_memory_service_ts", "target": "f_dev_clover_apps_backend_src_memory_obsidian_adapter_ts", "relation": "imports_from", "context": "import", "confidence": "EXTRACTED", "source_file": "F:\\Dev\\Clover\\apps\\backend\\src\\memory\\memory.service.ts", "source_location": "L8", "weight": 1.0}, {"source": "f_dev_clover_apps_backend_src_memory_memory_service_ts", "target": "f_dev_clover_apps_backend_src_memory_obsidian_adapter_ts", "relation": "imports_from", "context": "import", "confidence": "EXTRACTED", "source_file": "F:\\Dev\\Clover\\apps\\backend\\src\\memory\\memory.service.ts", "source_location": "L9", "weight": 1.0}, {"source": "f_dev_clover_apps_backend_src_memory_memory_service_ts", "target": "memory_obsidian_adapter_writemode", "relation": "imports", "context": "import", "confidence": "EXTRACTED", "source_file": "F:\\Dev\\Clover\\apps\\backend\\src\\memory\\memory.service.ts", "source_location": "L9", "weight": 1.0}, {"source": "f_dev_clover_apps_backend_src_memory_memory_service_ts", "target": "memory_memory_service_search", "relation": "contains", "confidence": "EXTRACTED", "source_file": "F:\\Dev\\Clover\\apps\\backend\\src\\memory\\memory.service.ts", "source_location": "L14", "weight": 1.0}, {"source": "f_dev_clover_apps_backend_src_memory_memory_service_ts", "target": "memory_memory_service_indextext", "relation": "contains", "confidence": "EXTRACTED", "source_file": "F:\\Dev\\Clover\\apps\\backend\\src\\memory\\memory.service.ts", "source_location": "L28", "weight": 1.0}, {"source": "f_dev_clover_apps_backend_src_memory_memory_service_ts", "target": "memory_memory_service_indexfile", "relation": "contains", "confidence": "EXTRACTED", "source_file": "F:\\Dev\\Clover\\apps\\backend\\src\\memory\\memory.service.ts", "source_location": "L43", "weight": 1.0}, {"source": "f_dev_clover_apps_backend_src_memory_memory_service_ts", "target": "memory_memory_service_ingestdirectory", "relation": "contains", "confidence": "EXTRACTED", "source_file": "F:\\Dev\\Clover\\apps\\backend\\src\\memory\\memory.service.ts", "source_location": "L56", "weight": 1.0}, {"source": "f_dev_clover_apps_backend_src_memory_memory_service_ts", "target": "memory_memory_service_writenote", "relation": "contains", "confidence": "EXTRACTED", "source_file": "F:\\Dev\\Clover\\apps\\backend\\src\\memory\\memory.service.ts", "source_location": "L70", "weight": 1.0}, {"source": "f_dev_clover_apps_backend_src_memory_memory_service_ts", "target": "memory_memory_service_tovectorchunks", "relation": "contains", "confidence": "EXTRACTED", "source_file": "F:\\Dev\\Clover\\apps\\backend\\src\\memory\\memory.service.ts", "source_location": "L84", "weight": 1.0}, {"source": "memory_memory_service_indextext", "target": "memory_memory_service_tovectorchunks", "relation": "calls", "context": "call", "confidence": "EXTRACTED", "source_file": "F:\\Dev\\Clover\\apps\\backend\\src\\memory\\memory.service.ts", "source_location": "L35", "weight": 1.0}, {"source": "memory_memory_service_indexfile", "target": "memory_memory_service_tovectorchunks", "relation": "calls", "context": "call", "confidence": "EXTRACTED", "source_file": "F:\\Dev\\Clover\\apps\\backend\\src\\memory\\memory.service.ts", "source_location": "L48", "weight": 1.0}, {"source": "memory_memory_service_ingestdirectory", "target": "memory_memory_service_indexfile", "relation": "calls", "context": "call", "confidence": "EXTRACTED", "source_file": "F:\\Dev\\Clover\\apps\\backend\\src\\memory\\memory.service.ts", "source_location": "L63", "weight": 1.0}], "raw_calls": [{"caller_nid": "memory_memory_service_search", "callee": "embed", "is_member_call": false, "source_file": "F:\\Dev\\Clover\\apps\\backend\\src\\memory\\memory.service.ts", "source_location": "L19"}, {"caller_nid": "memory_memory_service_search", "callee": "similaritySearch", "is_member_call": true, "source_file": "F:\\Dev\\Clover\\apps\\backend\\src\\memory\\memory.service.ts", "source_location": "L21"}, {"caller_nid": "memory_memory_service_indextext", "callee": "split", "is_member_call": false, "source_file": "F:\\Dev\\Clover\\apps\\backend\\src\\memory\\memory.service.ts", "source_location": "L32"}, {"caller_nid": "memory_memory_service_indextext", "callee": "insert", "is_member_call": true, "source_file": "F:\\Dev\\Clover\\apps\\backend\\src\\memory\\memory.service.ts", "source_location": "L36"}, {"caller_nid": "memory_memory_service_indexfile", "callee": "read", "is_member_call": true, "source_file": "F:\\Dev\\Clover\\apps\\backend\\src\\memory\\memory.service.ts", "source_location": "L44"}, {"caller_nid": "memory_memory_service_indexfile", "callee": "split", "is_member_call": false, "source_file": "F:\\Dev\\Clover\\apps\\backend\\src\\memory\\memory.service.ts", "source_location": "L45"}, {"caller_nid": "memory_memory_service_indexfile", "callee": "upsertByPath", "is_member_call": true, "source_file": "F:\\Dev\\Clover\\apps\\backend\\src\\memory\\memory.service.ts", "source_location": "L49"}, {"caller_nid": "memory_memory_service_ingestdirectory", "callee": "readdir", "is_member_call": false, "source_file": "F:\\Dev\\Clover\\apps\\backend\\src\\memory\\memory.service.ts", "source_location": "L57"}, {"caller_nid": "memory_memory_service_ingestdirectory", "callee": "map", "is_member_call": true, "source_file": "F:\\Dev\\Clover\\apps\\backend\\src\\memory\\memory.service.ts", "source_location": "L58"}, {"caller_nid": "memory_memory_service_ingestdirectory", "callee": "filter", "is_member_call": true, "source_file": "F:\\Dev\\Clover\\apps\\backend\\src\\memory\\memory.service.ts", "source_location": "L58"}, {"caller_nid": "memory_memory_service_tovectorchunks", "callee": "toISOString", "is_member_call": true, "source_file": "F:\\Dev\\Clover\\apps\\backend\\src\\memory\\memory.service.ts", "source_location": "L88"}, {"caller_nid": "memory_memory_service_tovectorchunks", "callee": "embed", "is_member_call": false, "source_file": "F:\\Dev\\Clover\\apps\\backend\\src\\memory\\memory.service.ts", "source_location": "L92"}, {"caller_nid": "memory_memory_service_tovectorchunks", "callee": "push", "is_member_call": true, "source_file": "F:\\Dev\\Clover\\apps\\backend\\src\\memory\\memory.service.ts", "source_location": "L93"}]}