{"nodes": [{"id": "f_dev_clover_apps_backend_src_tools_plugins_execute_command_tool_ts", "label": "execute-command.tool.ts", "file_type": "code", "source_file": "F:\\Dev\\Clover\\apps\\backend\\src\\tools\\plugins\\execute-command.tool.ts", "source_location": "L1"}], "edges": [{"source": "f_dev_clover_apps_backend_src_tools_plugins_execute_command_tool_ts", "target": "node_path", "relation": "imports_from", "context": "import", "confidence": "EXTRACTED", "source_file": "F:\\Dev\\Clover\\apps\\backend\\src\\tools\\plugins\\execute-command.tool.ts", "source_location": "L11", "weight": 1.0}, {"source": "f_dev_clover_apps_backend_src_tools_plugins_execute_command_tool_ts", "target": "zod", "relation": "imports_from", "context": "import", "confidence": "EXTRACTED", "source_file": "F:\\Dev\\Clover\\apps\\backend\\src\\tools\\plugins\\execute-command.tool.ts", "source_location": "L12", "weight": 1.0}, {"source": "f_dev_clover_apps_backend_src_tools_plugins_execute_command_tool_ts", "target": "shared", "relation": "imports_from", "context": "import", "confidence": "EXTRACTED", "source_file": "F:\\Dev\\Clover\\apps\\backend\\src\\tools\\plugins\\execute-command.tool.ts", "source_location": "L13", "weight": 1.0}, {"source": "f_dev_clover_apps_backend_src_tools_plugins_execute_command_tool_ts", "target": "f_dev_clover_apps_backend_src_exec_guard_exec_guard_ts", "relation": "imports_from", "context": "import", "confidence": "EXTRACTED", "source_file": "F:\\Dev\\Clover\\apps\\backend\\src\\tools\\plugins\\execute-command.tool.ts", "source_location": "L14", "weight": 1.0}, {"source": "f_dev_clover_apps_backend_src_tools_plugins_execute_command_tool_ts", "target": "exec_guard_exec_guard_run", "relation": "imports", "context": "import", "confidence": "EXTRACTED", "source_file": "F:\\Dev\\Clover\\apps\\backend\\src\\tools\\plugins\\execute-command.tool.ts", "source_location": "L14", "weight": 1.0}], "raw_calls": []}